pywolf8/__init__.py
pywolf8/ism8.py
pywolf8-0.4.dist-info/METADATA
pywolf8-0.4.dist-info/WHEEL
pywolf8-0.4.dist-info/licenses/LICENSE
pywolf8-0.4.dist-info/RECORD
