Metadata-Version: 2.1
Name: pywolf8
Version: 0.4
Summary: api to use with home assistant
Project-URL: Homepage, https://github.com/maxibick/pywolf8
Project-URL: Bug Tracker, https://github.com/maxibick/pywolf8/issues
Author-email: maxibick <author@example.com>
License: MIT License
License-File: LICENSE
Classifier: License :: OSI Approved :: MIT License
Classifier: Operating System :: OS Independent
Classifier: Programming Language :: Python :: 3
Requires-Python: >=3.7
